<?xml version="1.0" encoding="UTF-8" standalone="yes"?><response><header><resultCode>00</resultCode><resultMsg>NORMAL SERVICE.</resultMsg></header><body><items><item><aprEng>GIMPO INTERNATIONAL AIRPORT</aprEng><aprKor>김포국제공항</aprKor><parkingAirportCodeName>국내선 제1주차장</parkingAirportCodeName><parkingFullSpace>2279</parkingFullSpace><parkingGetdate>2025-06-11</parkingGetdate><parkingGettime>10:48:02</parkingGettime><parkingIincnt>1154</parkingIincnt><parkingIoutcnt>302</parkingIoutcnt><parkingIstay>2153</parkingIstay></item><item><aprEng>GIMPO INTERNATIONAL AIRPORT</aprEng><aprKor>김포국제공항</aprKor><parkingAirportCodeName>국내선 제2주차장</parkingAirportCodeName><parkingFullSpace>1733</parkingFullSpace><parkingGetdate>2025-06-11</parkingGetdate><parkingGettime>10:48:02</parkingGettime><parkingIincnt>584</parkingIincnt><parkingIoutcnt>137</parkingIoutcnt><parkingIstay>1364</parkingIstay></item><item><aprEng>GIMPO INTERNATIONAL AIRPORT</aprEng><aprKor>김포국제공항</aprKor><parkingAirportCodeName>국제선 주차빌딩</parkingAirportCodeName><parkingFullSpace>567</parkingFullSpace><parkingGetdate>2025-06-11</parkingGetdate><parkingGettime>10:48:02</parkingGettime><parkingIincnt>247</parkingIincnt><parkingIoutcnt>107</parkingIoutcnt><parkingIstay>399</parkingIstay></item><item><aprEng>GIMPO INTERNATIONAL AIRPORT</aprEng><aprKor>김포국제공항</aprKor><parkingAirportCodeName>국제선 지하</parkingAirportCodeName><parkingFullSpace>599</parkingFullSpace><parkingGetdate>2025-06-11</parkingGetdate><parkingGettime>10:48:02</parkingGettime><parkingIincnt>274</parkingIincnt><parkingIoutcnt>50</parkingIoutcnt><parkingIstay>547</parkingIstay></item><item><aprEng>GIMPO INTERNATIONAL AIRPORT</aprEng><aprKor>김포국제공항</aprKor><parkingAirportCodeName>화물청사</parkingAirportCodeName><parkingFullSpace>737</parkingFullSpace><parkingGetdate>2025-06-11</parkingGetdate><parkingGettime>10:48:02</parkingGettime><parkingIincnt>1699</parkingIincnt><parkingIoutcnt>821</parkingIoutcnt><parkingIstay>737</parkingIstay></item><item><aprEng>GIMHAE INTERNATIONAL AIRPORT</aprEng><aprKor>김해국제공항</aprKor><parkingAirportCodeName>P1 여객주차장</parkingAirportCodeName><parkingFullSpace>2005</parkingFullSpace><parkingGetdate>2025-06-11</parkingGetdate><parkingGettime>10:48:02</parkingGettime><parkingIincnt>786</parkingIincnt><parkingIoutcnt>274</parkingIoutcnt><parkingIstay>2005</parkingIstay></item><item><aprEng>GIMHAE INTERNATIONAL AIRPORT</aprEng><aprKor>김해국제공항</aprKor><parkingAirportCodeName>P2 여객주차장</parkingAirportCodeName><parkingFullSpace>2453</parkingFullSpace><parkingGetdate>2025-06-11</parkingGetdate><parkingGettime>10:48:02</parkingGettime><parkingIincnt>500</parkingIincnt><parkingIoutcnt>347</parkingIoutcnt><parkingIstay>2453</parkingIstay></item><item><aprEng>GIMHAE INTERNATIONAL AIRPORT</aprEng><aprKor>김해국제공항</aprKor><parkingAirportCodeName>P3 여객(화물)</parkingAirportCodeName><parkingFullSpace>878</parkingFullSpace><parkingGetdate>2025-06-11</parkingGetdate><parkingGettime>10:48:02</parkingGettime><parkingIincnt>396</parkingIincnt><parkingIoutcnt>216</parkingIoutcnt><parkingIstay>742</parkingIstay></item><item><aprEng>JEJU INTERNATIONAL AIRPORT</aprEng><aprKor>제주국제공항</aprKor><parkingAirportCodeName>P1주차장</parkingAirportCodeName><parkingFullSpace>1763</parkingFullSpace><parkingGetdate>2025-06-11</parkingGetdate><parkingGettime>10:48:02</parkingGettime><parkingIincnt>2080</parkingIincnt><parkingIoutcnt>1121</parkingIoutcnt><parkingIstay>1763</parkingIstay></item><item><aprEng>JEJU INTERNATIONAL AIRPORT</aprEng><aprKor>제주국제공항</aprKor><parkingAirportCodeName>P2장기주차장</parkingAirportCodeName><parkingFullSpace>488</parkingFullSpace><parkingGetdate>2025-06-11</parkingGetdate><parkingGettime>10:48:02</parkingGettime><parkingIincnt>237</parkingIincnt><parkingIoutcnt>33</parkingIoutcnt><parkingIstay>488</parkingIstay></item><item><aprEng>JEJU INTERNATIONAL AIRPORT</aprEng><aprKor>제주국제공항</aprKor><parkingAirportCodeName>화물주차장</parkingAirportCodeName><parkingFullSpace>732</parkingFullSpace><parkingGetdate>2025-06-11</parkingGetdate><parkingGettime>10:48:02</parkingGettime><parkingIincnt>796</parkingIincnt><parkingIoutcnt>576</parkingIoutcnt><parkingIstay>732</parkingIstay></item><item><aprEng>DAEGU INTERNATIONAL AIRPORT</aprEng><aprKor>대구국제공항</aprKor><parkingAirportCodeName>여객주차장</parkingAirportCodeName><parkingFullSpace>1361</parkingFullSpace><parkingGetdate>2025-06-11</parkingGetdate><parkingGettime>10:48:03</parkingGettime><parkingIincnt>422</parkingIincnt><parkingIoutcnt>140</parkingIoutcnt><parkingIstay>1123</parkingIstay></item><item><aprEng>DAEGU INTERNATIONAL AIRPORT</aprEng><aprKor>대구국제공항</aprKor><parkingAirportCodeName>화물주차장</parkingAirportCodeName><parkingFullSpace>13</parkingFullSpace><parkingGetdate>2025-06-11</parkingGetdate><parkingGettime>10:48:03</parkingGettime><parkingIincnt>23</parkingIincnt><parkingIoutcnt>18</parkingIoutcnt><parkingIstay>13</parkingIstay></item><item><aprEng>GWANGJU AIRPORT</aprEng><aprKor>광주공항</aprKor><parkingAirportCodeName>여객주차장(제1+제2)</parkingAirportCodeName><parkingFullSpace>1176</parkingFullSpace><parkingGetdate>2025-06-11</parkingGetdate><parkingGettime>10:48:03</parkingGettime><parkingIincnt>897</parkingIincnt><parkingIoutcnt>556</parkingIoutcnt><parkingIstay>880</parkingIstay></item><item><aprEng>YEOSU AIRPORT</aprEng><aprKor>여수공항</aprKor><parkingAirportCodeName>여객주차장</parkingAirportCodeName><parkingFullSpace>852</parkingFullSpace><parkingGetdate>2025-06-11</parkingGetdate><parkingGettime>10:48:03</parkingGettime><parkingIincnt>281</parkingIincnt><parkingIoutcnt>119</parkingIoutcnt><parkingIstay>621</parkingIstay></item><item><aprEng>ULSAN AIRPORT</aprEng><aprKor>울산공항</aprKor><parkingAirportCodeName>여객주차장</parkingAirportCodeName><parkingFullSpace>454</parkingFullSpace><parkingGetdate>2025-06-11</parkingGetdate><parkingGettime>10:48:03</parkingGettime><parkingIincnt>81</parkingIincnt><parkingIoutcnt>45</parkingIoutcnt><parkingIstay>219</parkingIstay></item><item><aprEng>GUNSAN AIRPORT</aprEng><aprKor>군산공항</aprKor><parkingAirportCodeName>여객주차장</parkingAirportCodeName><parkingFullSpace>467</parkingFullSpace><parkingGetdate>2025-06-11</parkingGetdate><parkingGettime>10:48:03</parkingGettime><parkingIincnt>17</parkingIincnt><parkingIoutcnt>3</parkingIoutcnt><parkingIstay>199</parkingIstay></item><item><aprEng>WONJU AIRPORT</aprEng><aprKor>원주공항</aprKor><parkingAirportCodeName>여객주차장</parkingAirportCodeName><parkingFullSpace>139</parkingFullSpace><parkingGetdate>2025-06-11</parkingGetdate><parkingGettime>10:48:03</parkingGettime><parkingIincnt>54</parkingIincnt><parkingIoutcnt>23</parkingIoutcnt><parkingIstay>135</parkingIstay></item><item><aprEng>CHEONGJU INTERNATIONAL AIRPORT</aprEng><aprKor>청주국제공항</aprKor><parkingAirportCodeName>여객 제1주차장</parkingAirportCodeName><parkingFullSpace>2203</parkingFullSpace><parkingGetdate>2025-06-11</parkingGetdate><parkingGettime>10:48:03</parkingGettime><parkingIincnt>693</parkingIincnt><parkingIoutcnt>334</parkingIoutcnt><parkingIstay>2203</parkingIstay></item><item><aprEng>CHEONGJU INTERNATIONAL AIRPORT</aprEng><aprKor>청주국제공항</aprKor><parkingAirportCodeName>여객 제2주차장</parkingAirportCodeName><parkingFullSpace>1703</parkingFullSpace><parkingGetdate>2025-06-11</parkingGetdate><parkingGettime>10:48:03</parkingGettime><parkingIincnt>381</parkingIincnt><parkingIoutcnt>94</parkingIoutcnt><parkingIstay>1660</parkingIstay></item><item><aprEng>CHEONGJU INTERNATIONAL AIRPORT</aprEng><aprKor>청주국제공항</aprKor><parkingAirportCodeName>여객 제3주차장</parkingAirportCodeName><parkingFullSpace>808</parkingFullSpace><parkingGetdate>2025-06-11</parkingGetdate><parkingGettime>10:48:03</parkingGettime><parkingIincnt>255</parkingIincnt><parkingIoutcnt>33</parkingIoutcnt><parkingIstay>597</parkingIstay></item><item><aprEng>CHEONGJU INTERNATIONAL AIRPORT</aprEng><aprKor>청주국제공항</aprKor><parkingAirportCodeName>여객 제4주차장</parkingAirportCodeName><parkingFullSpace>463</parkingFullSpace><parkingGetdate>2025-06-11</parkingGetdate><parkingGettime>10:48:03</parkingGettime><parkingIincnt>64</parkingIincnt><parkingIoutcnt>28</parkingIoutcnt><parkingIstay>175</parkingIstay></item><item><aprEng>MUAN INTERNATIONAL AIRPORT</aprEng><aprKor>무안국제공항</aprKor><parkingAirportCodeName>여객주차장</parkingAirportCodeName><parkingFullSpace>2467</parkingFullSpace><parkingGetdate>2025-06-11</parkingGetdate><parkingGettime>10:48:03</parkingGettime><parkingIincnt>32</parkingIincnt><parkingIoutcnt>32</parkingIoutcnt><parkingIstay>0</parkingIstay></item><item><aprEng>SACHEON AIRPORT</aprEng><aprKor>사천공항</aprKor><parkingAirportCodeName>여객주차장</parkingAirportCodeName><parkingFullSpace>226</parkingFullSpace><parkingGetdate>2025-06-11</parkingGetdate><parkingGettime>10:48:03</parkingGettime><parkingIincnt>23</parkingIincnt><parkingIoutcnt>4</parkingIoutcnt><parkingIstay>166</parkingIstay></item><item><aprEng>YANGYANG INTERNATIONAL AIRPORT</aprEng><aprKor>양양국제공항</aprKor><parkingAirportCodeName>여객주차장</parkingAirportCodeName><parkingFullSpace>452</parkingFullSpace><parkingGetdate>2025-06-11</parkingGetdate><parkingGettime>10:48:03</parkingGettime><parkingIincnt>10</parkingIincnt><parkingIoutcnt>0</parkingIoutcnt><parkingIstay>238</parkingIstay></item></items></body></response>